PyMation/CustomItems.py
PyMation/__init__.py
PyMation/files.py
PyMation-0.1.1.dist-info/METADATA
PyMation-0.1.1.dist-info/WHEEL
PyMation-0.1.1.dist-info/top_level.txt
PyMation-0.1.1.dist-info/RECORD
