Metadata-Version: 2.1
Name: PyMation
Version: 0.1.1
Summary: An Python Automation package
Home-page: https://github.com/IvanVZabrodin/Automation
Author: Ivan Zabrodin
License: UNKNOWN
Platform: UNKNOWN
Classifier: Programming Language :: Python :: 3
Classifier: Operating System :: OS Independent
Requires-Python: >=3.6
